opopoppo/__init__.py
opopoppo/core.py
opopoppo/log.py
opopoppo/server.py
opopoppo-0.1.1.dist-info/METADATA
opopoppo-0.1.1.dist-info/WHEEL
opopoppo-0.1.1.dist-info/top_level.txt
opopoppo-0.1.1.dist-info/RECORD
